xenon/__init__.py
xenon/__main__.py
xenon/api.py
xenon/core.py
xenon/repository.py
xenon-0.9.2.dist-info/LICENSE
xenon-0.9.2.dist-info/METADATA
xenon-0.9.2.dist-info/WHEEL
xenon-0.9.2.dist-info/entry_points.txt
xenon-0.9.2.dist-info/top_level.txt
xenon-0.9.2.dist-info/RECORD
